uvbump/__init__.py
uvbump/__main__.py
uvbump/core.py
uvbump/npm.py
uvbump/py.typed
uvbump/uv.py
uvbump_cli-1.5.0.dist-info/METADATA
uvbump_cli-1.5.0.dist-info/WHEEL
uvbump_cli-1.5.0.dist-info/entry_points.txt
uvbump_cli-1.5.0.dist-info/licenses/LICENSE
uvbump_cli-1.5.0.dist-info/RECORD
