Metadata-Version: 2.4
Name: uvbump-cli
Version: 1.5.0
Summary: CLI to audit uv-managed dependency pins across a workspace
Author: griffinboris
License-Expression: MIT
License-File: LICENSE
Keywords: cli,dependencies,packaging,uv,versioning
Classifier: Development Status :: 3 - Alpha
Classifier: Intended Audience :: Developers
Classifier: License :: OSI Approved :: MIT License
Classifier: Operating System :: OS Independent
Classifier: Programming Language :: Python
Classifier: Programming Language :: Python :: 3
Classifier: Programming Language :: Python :: 3.12
Classifier: Programming Language :: Python :: 3.13
Requires-Python: >=3.12
Requires-Dist: packaging>=24.2
Requires-Dist: tomlkit>=0.13.2
